ProgressedHttp/__init__.py
ProgressedHttp/http.py
ProgressedHttp/progress.py
ProgressedHttp/utils.py
progressed_http-1.0.0.dist-info/DESCRIPTION.rst
progressed_http-1.0.0.dist-info/METADATA
progressed_http-1.0.0.dist-info/RECORD
progressed_http-1.0.0.dist-info/WHEEL
progressed_http-1.0.0.dist-info/metadata.json
progressed_http-1.0.0.dist-info/top_level.txt
