Metadata-Version: 1.1
Name: progressed-http
Version: 1.0.0
Summary: Personal http req/resp handler with origin progress bar support
Home-page: https://github.com/hellflame/progressed-http
Author: hellflame
Author-email: hellflamedly@gmail.com
License: MIT
Keywords: http req/resp handle,progress bar,simple
Platform: UNKNOWN
Classifier: Development Status :: 4 - Beta
Classifier: Intended Audience :: Developers
Classifier: License :: OSI Approved :: MIT License
Classifier: Environment :: Console
Classifier: Operating System :: MacOS
Classifier: Operating System :: MacOS :: MacOS X
Classifier: Operating System :: POSIX
Classifier: Operating System :: POSIX :: Linux
Classifier: Programming Language :: Python :: 2.7
Classifier: Programming Language :: Python :: 3.5
Classifier: Programming Language :: Python :: 3.6
